pywinstyles/__init__.py
pywinstyles/py_win_style.py
pywinstyles-1.8.dist-info/LICENSE
pywinstyles-1.8.dist-info/METADATA
pywinstyles-1.8.dist-info/WHEEL
pywinstyles-1.8.dist-info/top_level.txt
pywinstyles-1.8.dist-info/RECORD
