Metadata-Version: 2.1
Name: pywinstyles
Version: 1.8
Summary:  Customize window styles in windows 11
Home-page: https://github.com/Akascape/py-window-styles
Author: Akash Bora
License: Creative Commons Zero v1.0 Universal
Keywords: window-styles,pywinstyles,pywindowstyles,customtkinter,tkinter,python-window-themes,gui,python-gui,pyqt,title-bar,title-bar-color,windows-themes,wxpython,windows11
Classifier: License :: CC0 1.0 Universal (CC0 1.0) Public Domain Dedication
Classifier: Programming Language :: Python :: 3
Classifier: Operating System :: OS Independent
Requires-Python: >=3.8
License-File: LICENSE
